dsa_package/__init__.py
dsa_package/data_structures/__init__.py
dsa_package/data_structures/ds.py
dsa_package_data_structures-0.0.5.dist-info/METADATA
dsa_package_data_structures-0.0.5.dist-info/WHEEL
dsa_package_data_structures-0.0.5.dist-info/top_level.txt
dsa_package_data_structures-0.0.5.dist-info/RECORD
